{
  "games" : {
    "duelwithdragons" : {
      "attendees" : {
        "alex" : {
          "color" : "red"
        },
        "tom" : {
          "color" : "red"
        }
      },
      "name" : "Duel with Dragons",
      "type" : "quest"
    },
    "fightwithoctobruce" : {
      "attendees" : [ "tom", "alex", "jeremy", "mike" ],
      "name" : "Fight With OctoBruise",
      "type" : "quest"
    },
    "vanquishthevirusvillain" : {
      "attendees" : [ "tom" ],
      "name" : "Vanquish the Virus Villain",
      "type" : "quest"
    }
  },
  "sessions" : {
    "duelwithdragons" : {
      "attendees" : {
        "alex" : {
          "-K1V27sXHW6PTJD0pWbM" : {
            "character" : {
              "name" : "Bird",
              "size" : {
                "message" : "60",
                "pick" : "100"
              },
              "type" : "mobimon",
              "url" : "../../images/bird.svg",
              "viewBox" : {
                "full" : "0 0 68 148",
                "speaking" : "-15 0 100 120"
              }
            },
            "message" : "Test message yo!",
            "sender" : "tom"
          }
        },
        "tom" : {
          "-K1V4hvA-jqWZEuRG6ZS" : {
            "character" : {
              "name" : "Peater",
              "size" : {
                "message" : "60",
                "pick" : "100"
              },
              "type" : "mobimon",
              "url" : "../../images/peater.svg",
              "viewBox" : {
                "full" : "0 0 121 145",
                "speaking" : "30 0 60 90"
              }
            },
            "message" : "Test message yo!",
            "sender" : "alex"
          },
          "-K1V6cuitsoPobLWTmCh" : {
            "character" : {
              "name" : "Bilsner",
              "size" : {
                "message" : "60",
                "pick" : "100"
              },
              "type" : "mobimon",
              "url" : "../../images/bilsner.svg",
              "viewBox" : {
                "full" : "0 0 116 133",
                "speaking" : "10 0 100 70"
              }
            },
            "message" : "Test message yo!",
            "sender" : "alex"
          }
        }
      },
      "name" : "Duel with Dragons"
    },
    "vanquishthevirusvillain" : {
      "attendees" : {
        "tom" : {
          "color" : "red"
        }
      },
      "name" : "Vanquish the Virus Villain"
    }
  }
}
